geospatial/__init__.py
geospatial/geospatial.py
geospatial-0.11.6.dist-info/licenses/LICENSE
geospatial-0.11.6.dist-info/METADATA
geospatial-0.11.6.dist-info/WHEEL
geospatial-0.11.6.dist-info/top_level.txt
geospatial-0.11.6.dist-info/RECORD
