Metadata-Version: 2.4
Name: geospatial
Version: 0.11.6
Summary: A Python package for installing commonly used packages for geospatial analysis and data visualization with only one command.
Author-email: Qiusheng Wu <giswqs@gmail.com>
License: MIT license
Project-URL: Homepage, https://github.com/opengeos/geospatial
Keywords: geospatial
Classifier: Development Status :: 2 - Pre-Alpha
Classifier: Intended Audience :: Developers
Classifier: License :: OSI Approved :: MIT License
Classifier: Natural Language :: English
Classifier: Programming Language :: Python :: 3
Classifier: Programming Language :: Python :: 3.9
Classifier: Programming Language :: Python :: 3.10
Classifier: Programming Language :: Python :: 3.11
Classifier: Programming Language :: Python :: 3.12
Requires-Python: >=3.9
License-File: LICENSE
Requires-Dist: apache-sedona
Requires-Dist: bokeh
Requires-Dist: cenpy
Requires-Dist: contextily
Requires-Dist: cubo
Requires-Dist: dask-ee
Requires-Dist: dask-geopandas
Requires-Dist: datashader
Requires-Dist: duckdb
Requires-Dist: earthaccess
Requires-Dist: earthengine-api
Requires-Dist: earthpy
Requires-Dist: easystac
Requires-Dist: eemont
Requires-Dist: eoreader
Requires-Dist: fiona
Requires-Dist: folium
Requires-Dist: geemap>=0.35.0
Requires-Dist: geoalchemy2
Requires-Dist: geocube
Requires-Dist: geopandas
Requires-Dist: geotiff
Requires-Dist: h3
Requires-Dist: hvplot
Requires-Dist: hypercoast
Requires-Dist: ipygany
Requires-Dist: ipyleaflet
Requires-Dist: laspy
Requires-Dist: leafmap>=0.47.2
Requires-Dist: localtileserver
Requires-Dist: mapboxgl
Requires-Dist: mapclassify
Requires-Dist: maplibre
Requires-Dist: mapwidget
Requires-Dist: movingpandas
Requires-Dist: mss
Requires-Dist: netcdf4
Requires-Dist: networkx
Requires-Dist: odc-stac
Requires-Dist: osmnx
Requires-Dist: overturemaps
Requires-Dist: owslib
Requires-Dist: palettable
Requires-Dist: panel
Requires-Dist: planetary-computer
Requires-Dist: plotly
Requires-Dist: pygis>=0.7.0
Requires-Dist: pyntcloud
Requires-Dist: pyproj
Requires-Dist: pysal
Requires-Dist: pyshp
Requires-Dist: pystac-client
Requires-Dist: rasterio
Requires-Dist: rasterstats
Requires-Dist: rio-cogeo
Requires-Dist: rioxarray
Requires-Dist: s2cloudless
Requires-Dist: sarpy
Requires-Dist: satpy
Requires-Dist: sentinelsat
Requires-Dist: shapely
Requires-Dist: simplekml
Requires-Dist: sliderule
Requires-Dist: solara
Requires-Dist: spyndex
Requires-Dist: sqlalchemy
Requires-Dist: stackstac
Requires-Dist: usgs
Requires-Dist: voila
Requires-Dist: whitebox
Requires-Dist: whiteboxgui
Requires-Dist: wxee
Requires-Dist: xarray
Requires-Dist: xarray-spatial
Requires-Dist: xee
Requires-Dist: xyzservices
Provides-Extra: all
Requires-Dist: lidar; extra == "all"
Requires-Dist: xcube; extra == "all"
Dynamic: license-file
